sudoku/__init__.py
sudoku/__main__.py
sudoku/dlx.py
sudoku/grid.py
sudoku/sample_puzzles.py
sudoku/solver.py
sudoku/ui.py
sudoku/utils/__init__.py
sudoku/utils/colorize.py
sudoku/utils/event.py
sudoku_ui-1.0.3.dist-info/LICENSE
sudoku_ui-1.0.3.dist-info/METADATA
sudoku_ui-1.0.3.dist-info/WHEEL
sudoku_ui-1.0.3.dist-info/entry_points.txt
sudoku_ui-1.0.3.dist-info/RECORD
