Metadata-Version: 2.1
Name: sudoku-ui
Version: 1.0.3
Summary: Solve sudoku puzzles using various algorithms
Home-page: https://github.com/will2dye4/sudoku.git
License: MIT
Keywords: dancing links,dlx,sudoku,sudoku solver
Author: William Dye
Requires-Python: >=3.7,<4.0
Classifier: License :: OSI Approved :: MIT License
Classifier: Programming Language :: Python :: 3
Classifier: Programming Language :: Python :: 3.7
Classifier: Programming Language :: Python :: 3.8
Classifier: Programming Language :: Python :: 3.9
Classifier: Programming Language :: Python :: 3.10
Classifier: Programming Language :: Python :: 3.11
Project-URL: Repository, https://github.com/will2dye4/sudoku.git
